gitingest_mcp/__init__.py
gitingest_mcp/server.py
trelis_gitingest_mcp-1.1.2.dist-info/METADATA
trelis_gitingest_mcp-1.1.2.dist-info/WHEEL
trelis_gitingest_mcp-1.1.2.dist-info/entry_points.txt
trelis_gitingest_mcp-1.1.2.dist-info/licenses/LICENSE
trelis_gitingest_mcp-1.1.2.dist-info/RECORD
