Metadata-Version: 2.4
Name: trelis-gitingest-mcp
Version: 1.1.2
Summary: An MCP server for gitingest
Author-email: RonanMcGovern <78278410+RonanKMcGovern@users.noreply.github.com>
License-File: LICENSE
Requires-Python: >=3.12
Requires-Dist: gitingest
Requires-Dist: mcp>=1.9.3
Requires-Dist: pathspec
